clang/__init__.py
clang/cindex.py
clang/enumerations.py
cppbind/__init__.py
cppbind/runner.py
cppbind/builder/__init__.py
cppbind/builder/ir_builder.py
cppbind/builder/ir_post_processor.py
cppbind/builder/out_builder.py
cppbind/common/__init__.py
cppbind/common/config.py
cppbind/common/error.py
cppbind/common/snippets_engine.py
cppbind/common/type_info.py
cppbind/common/yaml_process.py
cppbind/config/cppbind.yaml
cppbind/config/cppbind_config.cfg
cppbind/config/cxx_macros.yaml
cppbind/config/modulemap_variable_definitions.yaml
cppbind/config/variable_definitions.yaml
cppbind/config/rules/snippets.py
cppbind/config/snippets/common_macros.yaml
cppbind/config/snippets/kotlin/actions.yaml
cppbind/config/snippets/kotlin/basic_cppbind_types.yaml
cppbind/config/snippets/kotlin/code_snippets.yaml
cppbind/config/snippets/kotlin/complex_cppbind_types.yaml
cppbind/config/snippets/kotlin/kotlin_macros.yaml
cppbind/config/snippets/python/actions.yaml
cppbind/config/snippets/python/basic_cppbind_types.yaml
cppbind/config/snippets/python/bind_snippet.yaml
cppbind/config/snippets/python/code_snippets.yaml
cppbind/config/snippets/python/complex_cppbind_types.yaml
cppbind/config/snippets/python/python_macros.yaml
cppbind/config/snippets/swift/actions.yaml
cppbind/config/snippets/swift/basic_cppbind_types.yaml
cppbind/config/snippets/swift/code_snippets.yaml
cppbind/config/snippets/swift/complex_cppbind_types.yaml
cppbind/config/snippets/swift/modulemap_snippets.yaml
cppbind/config/snippets/swift/swift_macros.yaml
cppbind/config/std_exc/std_exc_api.yaml
cppbind/config/std_helpers/kotlin/exceptionUtils.kt
cppbind/config/std_helpers/kotlin/utils.kt
cppbind/config/std_helpers/kotlin/cxx/c_helpers.h
cppbind/config/std_helpers/kotlin/cxx/cppbind_wrapper_helper.hpp
cppbind/config/std_helpers/python/cppbind_metaclass.py
cppbind/config/std_helpers/swift/exceptionUtils.swift
cppbind/config/std_helpers/swift/cxx/c_helpers.h
cppbind/config/std_helpers/swift/cxx/cppbind_wrapper_helper.hpp
cppbind-1.0.3.dist-info/LICENSE
cppbind-1.0.3.dist-info/METADATA
cppbind-1.0.3.dist-info/WHEEL
cppbind-1.0.3.dist-info/entry_points.txt
cppbind-1.0.3.dist-info/top_level.txt
cppbind-1.0.3.dist-info/RECORD
