Metadata-Version: 2.1
Name: cppbind
Version: 1.0.3
Summary: C++ bindings generator for various languages
Home-page: https://github.com/PicsArt/cppbind
Author: Picsart
Author-email: info@cppbind.io
License: UNKNOWN
Project-URL: Documentation, https://cppbind.io/
Platform: UNKNOWN
Classifier: Programming Language :: Python :: 3
Classifier: Programming Language :: C++
Classifier: Programming Language :: Kotlin
Classifier: Development Status :: 3 - Alpha
Classifier: Intended Audience :: Developers
Classifier: License :: OSI Approved :: MIT License
Classifier: Operating System :: OS Independent
Classifier: Topic :: Software Development :: Code Generators
Requires-Python: >=3.8
License-File: LICENSE
Requires-Dist: cached-property (==1.5.2)
Requires-Dist: cachetools (==5.0.0)
Requires-Dist: coverage (==6.3.2)
Requires-Dist: GitPython (==3.1.17)
Requires-Dist: ipdb (==0.13.3)
Requires-Dist: isort (==5.9.3)
Requires-Dist: jedi (==0.17.2)
Requires-Dist: Jinja2 (==3.0.3)
Requires-Dist: pytest (==7.1.3)
Requires-Dist: PyYAML (==5.4)
Requires-Dist: sortedcontainers (==2.4.0)
Requires-Dist: twine (==3.8.0)
Requires-Dist: wheel (==0.36.2)
Requires-Dist: wcmatch (==8.4.1)
